{
  "resourceType": "StructureDefinition",
  "id": "MedicationRequest",
  "meta": {
    "lastUpdated": "2022-10-05T04:55:02.2778307+00:00"
  },
  "extension": [
    {
      "url": "https://fhir.kemkes.go.id/r4/StructureDefinition/structuredefinition-category",
      "valueString": "Clinical.Medications"
    },
    {
      "url": "https://fhir.kemkes.go.id/r4/StructureDefinition/structuredefinition-standards-status",
      "valueCode": "trial-use"
    },
    {
      "url": "https://fhir.kemkes.go.id/r4/StructureDefinition/structuredefinition-fmm",
      "valueInteger": 3
    },
    {
      "url": "https://fhir.kemkes.go.id/r4/StructureDefinition/structuredefinition-security-category",
      "valueCode": "patient"
    },
    {
      "url": "https://fhir.kemkes.go.id/r4/StructureDefinition/structuredefinition-wg",
      "valueCode": "phx"
    }
  ],
  "url": "https://fhir.pwskia.id//StructureDefinition/MedicationRequest",
  "name": "MedicationRequest",
  "status": "draft",
  "date": "2023-05-12T03:54:04.8907436+00:00",
  "publisher": "Health Level Seven International (Pharmacy)",
  "contact": [
    {
      "telecom": [
        {
          "system": "url",
          "value": "http://hl7.org/fhir"
        }
      ]
    },
    {
      "telecom": [
        {
          "system": "url",
          "value": "http://www.hl7.org/Special/committees/medication/index.cfm"
        }
      ]
    }
  ],
  "description": "An order or request for both supply of the medication and the instructions for administration of the medication to a patient. The resource is called \"MedicationRequest\" rather than \"MedicationPrescription\" or \"MedicationOrder\" to generalize the use across inpatient and outpatient settings, including care plans, etc., and to harmonize with workflow patterns.",
  "fhirVersion": "4.0.1",
  "mapping": [
    {
      "identity": "script10.6",
      "name": "Mapping to NCPDP SCRIPT 10.6",
      "uri": "http://ncpdp.org/SCRIPT10_6"
    },
    {
      "identity": "v2",
      "name": "HL7 v2 Mapping",
      "uri": "http://hl7.org/v2"
    },
    {
      "identity": "w5",
      "name": "FiveWs Pattern Mapping",
      "uri": "http://hl7.org/fhir/fivews"
    },
    {
      "identity": "workflow",
      "name": "Workflow Pattern",
      "uri": "http://hl7.org/fhir/workflow"
    }
  ],
  "kind": "resource",
  "abstract": false,
  "type": "MedicationRequest",
  "baseDefinition": "https://fhir.pwskia.id//StructureDefinition/DomainResource",
  "derivation": "specialization",
  "differential": {
    "element": [
      {
        "id": "MedicationRequest",
        "path": "MedicationRequest",
        "short": "Ordering of medication for patient or group",
        "definition": "An order or request for both supply of the medication and the instructions for administration of the medication to a patient. The resource is called \"MedicationRequest\" rather than \"MedicationPrescription\" or \"MedicationOrder\" to generalize the use across inpatient and outpatient settings, including care plans, etc., and to harmonize with workflow patterns.",
        "alias": [
          "Prescription",
          "Order"
        ],
        "mapping": [
          {
            "identity": "rim",
            "map": "CombinedMedicationRequest"
          },
          {
            "identity": "script10.6",
            "map": "Message/Body/NewRx"
          },
          {
            "identity": "workflow",
            "map": "Request"
          }
        ]
      }
    ]
  }
}
